{
  "stations": ["BIGFM", "DHAMAAL FM", "MYFM", "RADIO CITY"],
  "data": [
    {
      "adName": "RADIO CITY",
      "percentage": 5.18,
      "stations": [
        {
          "station": "BIGFM",
          "adCount": 0
        },
        {
          "station": "DHAMAAL FM",
          "adCount": 0
        },
        {
          "station": "MYFM",
          "adCount": 0
        },
        {
          "station": "RADIO CITY",
          "adCount": 778
        }
      ]
    },
    {
      "adName": "RAJMOTI SAGO",
      "percentage": 3.66,
      "stations": [
        {
          "station": "BIGFM",
          "adCount": 279
        },
        {
          "station": "DHAMAAL FM",
          "adCount": 0
        },
        {
          "station": "MYFM",
          "adCount": 270
        },
        {
          "station": "RADIO CITY",
          "adCount": 0
        }
      ]
    },
    {
      "adName": "CHITALE",
      "percentage": 3.37,
      "stations": [
        {
          "station": "BIGFM",
          "adCount": 0
        },
        {
          "station": "DHAMAAL FM",
          "adCount": 266
        },
        {
          "station": "MYFM",
          "adCount": 239
        },
        {
          "station": "RADIO CITY",
          "adCount": 0
        }
      ]
    },
    {
      "adName": "JYOTI KRANTI MULTISTATE",
      "percentage": 2.93,
      "stations": [
        {
          "station": "BIGFM",
          "adCount": 155
        },
        {
          "station": "DHAMAAL FM",
          "adCount": 138
        },
        {
          "station": "MYFM",
          "adCount": 147
        },
        {
          "station": "RADIO CITY",
          "adCount": 0
        }
      ]
    },
    {
      "adName": "CANARA BANK",
      "percentage": 2.2,
      "stations": [
        {
          "station": "BIGFM",
          "adCount": 154
        },
        {
          "station": "DHAMAAL FM",
          "adCount": 0
        },
        {
          "station": "MYFM",
          "adCount": 0
        },
        {
          "station": "RADIO CITY",
          "adCount": 176
        }
      ]
    },
    {
      "adName": "IMS COLLEGE",
      "percentage": 2.19,
      "stations": [
        {
          "station": "BIGFM",
          "adCount": 108
        },
        {
          "station": "DHAMAAL FM",
          "adCount": 0
        },
        {
          "station": "MYFM",
          "adCount": 6
        },
        {
          "station": "RADIO CITY",
          "adCount": 215
        }
      ]
    },
    {
      "adName": "BAIDNATH",
      "percentage": 1.91,
      "stations": [
        {
          "station": "BIGFM",
          "adCount": 287
        },
        {
          "station": "DHAMAAL FM",
          "adCount": 0
        },
        {
          "station": "MYFM",
          "adCount": 0
        },
        {
          "station": "RADIO CITY",
          "adCount": 0
        }
      ]
    },
    {
      "adName": "SATPUTE DAIRY",
      "percentage": 1.76,
      "stations": [
        {
          "station": "BIGFM",
          "adCount": 0
        },
        {
          "station": "DHAMAAL FM",
          "adCount": 131
        },
        {
          "station": "MYFM",
          "adCount": 133
        },
        {
          "station": "RADIO CITY",
          "adCount": 0
        }
      ]
    },
    {
      "adName": "SAI MAULI HOSPITAL",
      "percentage": 1.73,
      "stations": [
        {
          "station": "BIGFM",
          "adCount": 0
        },
        {
          "station": "DHAMAAL FM",
          "adCount": 141
        },
        {
          "station": "MYFM",
          "adCount": 118
        },
        {
          "station": "RADIO CITY",
          "adCount": 0
        }
      ]
    },
    {
      "adName": "DR ORTHO",
      "percentage": 1.67,
      "stations": [
        {
          "station": "BIGFM",
          "adCount": 37
        },
        {
          "station": "DHAMAAL FM",
          "adCount": 111
        },
        {
          "station": "MYFM",
          "adCount": 103
        },
        {
          "station": "RADIO CITY",
          "adCount": 0
        }
      ]
    },
    {
      "adName": "RAJMOTI",
      "percentage": 1.57,
      "stations": [
        {
          "station": "BIGFM",
          "adCount": 0
        },
        {
          "station": "DHAMAAL FM",
          "adCount": 235
        },
        {
          "station": "MYFM",
          "adCount": 0
        },
        {
          "station": "RADIO CITY",
          "adCount": 0
        }
      ]
    },
    {
      "adName": "PET SAFFA",
      "percentage": 1.55,
      "stations": [
        {
          "station": "BIGFM",
          "adCount": 90
        },
        {
          "station": "DHAMAAL FM",
          "adCount": 143
        },
        {
          "station": "MYFM",
          "adCount": 0
        },
        {
          "station": "RADIO CITY",
          "adCount": 0
        }
      ]
    },
    {
      "adName": "RAJPAL SALE",
      "percentage": 1.43,
      "stations": [
        {
          "station": "BIGFM",
          "adCount": 180
        },
        {
          "station": "DHAMAAL FM",
          "adCount": 0
        },
        {
          "station": "MYFM",
          "adCount": 34
        },
        {
          "station": "RADIO CITY",
          "adCount": 0
        }
      ]
    },
    {
      "adName": "RATANKAMAL CHAHA",
      "percentage": 1.41,
      "stations": [
        {
          "station": "BIGFM",
          "adCount": 211
        },
        {
          "station": "DHAMAAL FM",
          "adCount": 0
        },
        {
          "station": "MYFM",
          "adCount": 0
        },
        {
          "station": "RADIO CITY",
          "adCount": 0
        }
      ]
    },
    {
      "adName": "HOTEL SAGE AND SALT",
      "percentage": 1.39,
      "stations": [
        {
          "station": "BIGFM",
          "adCount": 0
        },
        {
          "station": "DHAMAAL FM",
          "adCount": 133
        },
        {
          "station": "MYFM",
          "adCount": 76
        },
        {
          "station": "RADIO CITY",
          "adCount": 0
        }
      ]
    },
    {
      "adName": "BULDANA URBAN COOPERATIVE CREDIT SOCIETY",
      "percentage": 1.37,
      "stations": [
        {
          "station": "BIGFM",
          "adCount": 0
        },
        {
          "station": "DHAMAAL FM",
          "adCount": 0
        },
        {
          "station": "MYFM",
          "adCount": 0
        },
        {
          "station": "RADIO CITY",
          "adCount": 205
        }
      ]
    },
    {
      "adName": "CHANDU KAKA SARAF JEWELLERS",
      "percentage": 1.36,
      "stations": [
        {
          "station": "BIGFM",
          "adCount": 0
        },
        {
          "station": "DHAMAAL FM",
          "adCount": 67
        },
        {
          "station": "MYFM",
          "adCount": 56
        },
        {
          "station": "RADIO CITY",
          "adCount": 81
        }
      ]
    },
    {
      "adName": "GHARRKUL",
      "percentage": 1.33,
      "stations": [
        {
          "station": "BIGFM",
          "adCount": 0
        },
        {
          "station": "DHAMAAL FM",
          "adCount": 104
        },
        {
          "station": "MYFM",
          "adCount": 95
        },
        {
          "station": "RADIO CITY",
          "adCount": 0
        }
      ]
    },
    {
      "adName": "DAVA INDIA",
      "percentage": 1.31,
      "stations": [
        {
          "station": "BIGFM",
          "adCount": 196
        },
        {
          "station": "DHAMAAL FM",
          "adCount": 0
        },
        {
          "station": "MYFM",
          "adCount": 0
        },
        {
          "station": "RADIO CITY",
          "adCount": 0
        }
      ]
    },
    {
      "adName": "GOVERNMENT OF MAHARASHTRA",
      "percentage": 1.27,
      "stations": [
        {
          "station": "BIGFM",
          "adCount": 14
        },
        {
          "station": "DHAMAAL FM",
          "adCount": 8
        },
        {
          "station": "MYFM",
          "adCount": 20
        },
        {
          "station": "RADIO CITY",
          "adCount": 149
        }
      ]
    },
    {
      "adName": "S. BURHADE SARAF",
      "percentage": 1.27,
      "stations": [
        {
          "station": "BIGFM",
          "adCount": 0
        },
        {
          "station": "DHAMAAL FM",
          "adCount": 103
        },
        {
          "station": "MYFM",
          "adCount": 87
        },
        {
          "station": "RADIO CITY",
          "adCount": 0
        }
      ]
    },
    {
      "adName": "HEAVENS HOLIDAYS",
      "percentage": 1.19,
      "stations": [
        {
          "station": "BIGFM",
          "adCount": 0
        },
        {
          "station": "DHAMAAL FM",
          "adCount": 92
        },
        {
          "station": "MYFM",
          "adCount": 87
        },
        {
          "station": "RADIO CITY",
          "adCount": 0
        }
      ]
    },
    {
      "adName": "RC SWAPPR",
      "percentage": 1.15,
      "stations": [
        {
          "station": "BIGFM",
          "adCount": 0
        },
        {
          "station": "DHAMAAL FM",
          "adCount": 0
        },
        {
          "station": "MYFM",
          "adCount": 0
        },
        {
          "station": "RADIO CITY",
          "adCount": 172
        }
      ]
    },
    {
      "adName": "SAHADEV JEWELLERS",
      "percentage": 1.14,
      "stations": [
        {
          "station": "BIGFM",
          "adCount": 0
        },
        {
          "station": "DHAMAAL FM",
          "adCount": 72
        },
        {
          "station": "MYFM",
          "adCount": 99
        },
        {
          "station": "RADIO CITY",
          "adCount": 0
        }
      ]
    },
    {
      "adName": "ECE INDIA",
      "percentage": 1.13,
      "stations": [
        {
          "station": "BIGFM",
          "adCount": 0
        },
        {
          "station": "DHAMAAL FM",
          "adCount": 85
        },
        {
          "station": "MYFM",
          "adCount": 71
        },
        {
          "station": "RADIO CITY",
          "adCount": 13
        }
      ]
    },
    {
      "adName": "LIC",
      "percentage": 1.11,
      "stations": [
        {
          "station": "BIGFM",
          "adCount": 0
        },
        {
          "station": "DHAMAAL FM",
          "adCount": 51
        },
        {
          "station": "MYFM",
          "adCount": 62
        },
        {
          "station": "RADIO CITY",
          "adCount": 53
        }
      ]
    },
    {
      "adName": "MALABAR GOLD&DAIMOND",
      "percentage": 1.08,
      "stations": [
        {
          "station": "BIGFM",
          "adCount": 54
        },
        {
          "station": "DHAMAAL FM",
          "adCount": 54
        },
        {
          "station": "MYFM",
          "adCount": 54
        },
        {
          "station": "RADIO CITY",
          "adCount": 0
        }
      ]
    },
    {
      "adName": "CAMEL",
      "percentage": 1.05,
      "stations": [
        {
          "station": "BIGFM",
          "adCount": 0
        },
        {
          "station": "DHAMAAL FM",
          "adCount": 116
        },
        {
          "station": "MYFM",
          "adCount": 41
        },
        {
          "station": "RADIO CITY",
          "adCount": 0
        }
      ]
    },
    {
      "adName": "GHARKUL",
      "percentage": 1.05,
      "stations": [
        {
          "station": "BIGFM",
          "adCount": 0
        },
        {
          "station": "DHAMAAL FM",
          "adCount": 0
        },
        {
          "station": "MYFM",
          "adCount": 0
        },
        {
          "station": "RADIO CITY",
          "adCount": 157
        }
      ]
    },
    {
      "adName": "QUALITY OIL",
      "percentage": 1.02,
      "stations": [
        {
          "station": "BIGFM",
          "adCount": 0
        },
        {
          "station": "DHAMAAL FM",
          "adCount": 0
        },
        {
          "station": "MYFM",
          "adCount": 0
        },
        {
          "station": "RADIO CITY",
          "adCount": 153
        }
      ]
    },
    {
      "adName": "SHRI CHHATRAPATI SHIVAJI MAHARAJ COLLEGE OF ENGINEERING",
      "percentage": 1.02,
      "stations": [
        {
          "station": "BIGFM",
          "adCount": 0
        },
        {
          "station": "DHAMAAL FM",
          "adCount": 79
        },
        {
          "station": "MYFM",
          "adCount": 74
        },
        {
          "station": "RADIO CITY",
          "adCount": 0
        }
      ]
    },
    {
      "adName": "PET SAFA",
      "percentage": 0.99,
      "stations": [
        {
          "station": "BIGFM",
          "adCount": 0
        },
        {
          "station": "DHAMAAL FM",
          "adCount": 0
        },
        {
          "station": "MYFM",
          "adCount": 149
        },
        {
          "station": "RADIO CITY",
          "adCount": 0
        }
      ]
    },
    {
      "adName": "HP",
      "percentage": 0.99,
      "stations": [
        {
          "station": "BIGFM",
          "adCount": 149
        },
        {
          "station": "DHAMAAL FM",
          "adCount": 0
        },
        {
          "station": "MYFM",
          "adCount": 0
        },
        {
          "station": "RADIO CITY",
          "adCount": 0
        }
      ]
    },
    {
      "adName": "PURSHOTTAM NARAYAN JEWELLERS",
      "percentage": 0.99,
      "stations": [
        {
          "station": "BIGFM",
          "adCount": 0
        },
        {
          "station": "DHAMAAL FM",
          "adCount": 0
        },
        {
          "station": "MYFM",
          "adCount": 0
        },
        {
          "station": "RADIO CITY",
          "adCount": 148
        }
      ]
    },
    {
      "adName": "DINESH SAREES",
      "percentage": 0.99,
      "stations": [
        {
          "station": "BIGFM",
          "adCount": 0
        },
        {
          "station": "DHAMAAL FM",
          "adCount": 66
        },
        {
          "station": "MYFM",
          "adCount": 82
        },
        {
          "station": "RADIO CITY",
          "adCount": 0
        }
      ]
    },
    {
      "adName": "NINE PEARLS HOSPITAL",
      "percentage": 0.98,
      "stations": [
        {
          "station": "BIGFM",
          "adCount": 0
        },
        {
          "station": "DHAMAAL FM",
          "adCount": 0
        },
        {
          "station": "MYFM",
          "adCount": 0
        },
        {
          "station": "RADIO CITY",
          "adCount": 147
        }
      ]
    },
    {
      "adName": "SUDHAN POLYMERS-KAJARIA GALAXY",
      "percentage": 0.95,
      "stations": [
        {
          "station": "BIGFM",
          "adCount": 0
        },
        {
          "station": "DHAMAAL FM",
          "adCount": 0
        },
        {
          "station": "MYFM",
          "adCount": 0
        },
        {
          "station": "RADIO CITY",
          "adCount": 142
        }
      ]
    },
    {
      "adName": "JYOTI KRANTI MULTI STATE",
      "percentage": 0.94,
      "stations": [
        {
          "station": "BIGFM",
          "adCount": 0
        },
        {
          "station": "DHAMAAL FM",
          "adCount": 0
        },
        {
          "station": "MYFM",
          "adCount": 0
        },
        {
          "station": "RADIO CITY",
          "adCount": 141
        }
      ]
    },
    {
      "adName": "EXCELLENCE AWARDS GLOBAL",
      "percentage": 0.91,
      "stations": [
        {
          "station": "BIGFM",
          "adCount": 0
        },
        {
          "station": "DHAMAAL FM",
          "adCount": 99
        },
        {
          "station": "MYFM",
          "adCount": 38
        },
        {
          "station": "RADIO CITY",
          "adCount": 0
        }
      ]
    },
    {
      "adName": "CAMEL SAGO",
      "percentage": 0.89,
      "stations": [
        {
          "station": "BIGFM",
          "adCount": 44
        },
        {
          "station": "DHAMAAL FM",
          "adCount": 0
        },
        {
          "station": "MYFM",
          "adCount": 90
        },
        {
          "station": "RADIO CITY",
          "adCount": 0
        }
      ]
    },
    {
      "adName": "DR.VITHALRAO VIKHE PATIL COLLEGE OF ENGINEERING",
      "percentage": 0.85,
      "stations": [
        {
          "station": "BIGFM",
          "adCount": 85
        },
        {
          "station": "DHAMAAL FM",
          "adCount": 0
        },
        {
          "station": "MYFM",
          "adCount": 42
        },
        {
          "station": "RADIO CITY",
          "adCount": 0
        }
      ]
    },
    {
      "adName": "KWALITY",
      "percentage": 0.84,
      "stations": [
        {
          "station": "BIGFM",
          "adCount": 126
        },
        {
          "station": "DHAMAAL FM",
          "adCount": 0
        },
        {
          "station": "MYFM",
          "adCount": 0
        },
        {
          "station": "RADIO CITY",
          "adCount": 0
        }
      ]
    },
    {
      "adName": "MENS AVENUE",
      "percentage": 0.82,
      "stations": [
        {
          "station": "BIGFM",
          "adCount": 63
        },
        {
          "station": "DHAMAAL FM",
          "adCount": 0
        },
        {
          "station": "MYFM",
          "adCount": 0
        },
        {
          "station": "RADIO CITY",
          "adCount": 60
        }
      ]
    },
    {
      "adName": "GODAVARI CBSE JUNIOR COLLEGE",
      "percentage": 0.81,
      "stations": [
        {
          "station": "BIGFM",
          "adCount": 0
        },
        {
          "station": "DHAMAAL FM",
          "adCount": 0
        },
        {
          "station": "MYFM",
          "adCount": 0
        },
        {
          "station": "RADIO CITY",
          "adCount": 122
        }
      ]
    },
    {
      "adName": "SIDDHI VASTUPURAM",
      "percentage": 0.81,
      "stations": [
        {
          "station": "BIGFM",
          "adCount": 0
        },
        {
          "station": "DHAMAAL FM",
          "adCount": 0
        },
        {
          "station": "MYFM",
          "adCount": 0
        },
        {
          "station": "RADIO CITY",
          "adCount": 122
        }
      ]
    },
    {
      "adName": "PANDURANG LAND DEVELOPERS",
      "percentage": 0.81,
      "stations": [
        {
          "station": "BIGFM",
          "adCount": 0
        },
        {
          "station": "DHAMAAL FM",
          "adCount": 0
        },
        {
          "station": "MYFM",
          "adCount": 0
        },
        {
          "station": "RADIO CITY",
          "adCount": 122
        }
      ]
    },
    {
      "adName": "BARVA SKIN",
      "percentage": 0.81,
      "stations": [
        {
          "station": "BIGFM",
          "adCount": 0
        },
        {
          "station": "DHAMAAL FM",
          "adCount": 0
        },
        {
          "station": "MYFM",
          "adCount": 0
        },
        {
          "station": "RADIO CITY",
          "adCount": 122
        }
      ]
    },
    {
      "adName": "RADIO FESTIVAL AWARD",
      "percentage": 0.81,
      "stations": [
        {
          "station": "BIGFM",
          "adCount": 0
        },
        {
          "station": "DHAMAAL FM",
          "adCount": 55
        },
        {
          "station": "MYFM",
          "adCount": 66
        },
        {
          "station": "RADIO CITY",
          "adCount": 0
        }
      ]
    },
    {
      "adName": "MACCARE",
      "percentage": 0.81,
      "stations": [
        {
          "station": "BIGFM",
          "adCount": 0
        },
        {
          "station": "DHAMAAL FM",
          "adCount": 0
        },
        {
          "station": "MYFM",
          "adCount": 0
        },
        {
          "station": "RADIO CITY",
          "adCount": 121
        }
      ]
    },
    {
      "adName": "ATHARE PATIL PUBLIC SCHOOL",
      "percentage": 0.8,
      "stations": [
        {
          "station": "BIGFM",
          "adCount": 0
        },
        {
          "station": "DHAMAAL FM",
          "adCount": 60
        },
        {
          "station": "MYFM",
          "adCount": 60
        },
        {
          "station": "RADIO CITY",
          "adCount": 0
        }
      ]
    },
    {
      "adName": "PRAKASH",
      "percentage": 0.77,
      "stations": [
        {
          "station": "BIGFM",
          "adCount": 0
        },
        {
          "station": "DHAMAAL FM",
          "adCount": 59
        },
        {
          "station": "MYFM",
          "adCount": 56
        },
        {
          "station": "RADIO CITY",
          "adCount": 0
        }
      ]
    },
    {
      "adName": "MUZAK DISCO",
      "percentage": 0.7,
      "stations": [
        {
          "station": "BIGFM",
          "adCount": 0
        },
        {
          "station": "DHAMAAL FM",
          "adCount": 0
        },
        {
          "station": "MYFM",
          "adCount": 0
        },
        {
          "station": "RADIO CITY",
          "adCount": 105
        }
      ]
    },
    {
      "adName": "BIGLIVE",
      "percentage": 0.7,
      "stations": [
        {
          "station": "BIGFM",
          "adCount": 105
        },
        {
          "station": "DHAMAAL FM",
          "adCount": 0
        },
        {
          "station": "MYFM",
          "adCount": 0
        },
        {
          "station": "RADIO CITY",
          "adCount": 0
        }
      ]
    },
    {
      "adName": "S BHURADE SARAF",
      "percentage": 0.69,
      "stations": [
        {
          "station": "BIGFM",
          "adCount": 103
        },
        {
          "station": "DHAMAAL FM",
          "adCount": 0
        },
        {
          "station": "MYFM",
          "adCount": 0
        },
        {
          "station": "RADIO CITY",
          "adCount": 0
        }
      ]
    },
    {
      "adName": "ORGAYU",
      "percentage": 0.68,
      "stations": [
        {
          "station": "BIGFM",
          "adCount": 102
        },
        {
          "station": "DHAMAAL FM",
          "adCount": 0
        },
        {
          "station": "MYFM",
          "adCount": 0
        },
        {
          "station": "RADIO CITY",
          "adCount": 0
        }
      ]
    },
    {
      "adName": "EVOLVE PRIMEAR",
      "percentage": 0.67,
      "stations": [
        {
          "station": "BIGFM",
          "adCount": 0
        },
        {
          "station": "DHAMAAL FM",
          "adCount": 0
        },
        {
          "station": "MYFM",
          "adCount": 0
        },
        {
          "station": "RADIO CITY",
          "adCount": 100
        }
      ]
    },
    {
      "adName": "SMT. RADHADEVI GOENKA COLLEGE",
      "percentage": 0.65,
      "stations": [
        {
          "station": "BIGFM",
          "adCount": 0
        },
        {
          "station": "DHAMAAL FM",
          "adCount": 55
        },
        {
          "station": "MYFM",
          "adCount": 42
        },
        {
          "station": "RADIO CITY",
          "adCount": 0
        }
      ]
    },
    {
      "adName": "RAJARAM BAPU SUGAR TECH COLLEGE",
      "percentage": 0.61,
      "stations": [
        {
          "station": "BIGFM",
          "adCount": 92
        },
        {
          "station": "DHAMAAL FM",
          "adCount": 0
        },
        {
          "station": "MYFM",
          "adCount": 0
        },
        {
          "station": "RADIO CITY",
          "adCount": 0
        }
      ]
    },
    {
      "adName": "SBI",
      "percentage": 0.61,
      "stations": [
        {
          "station": "BIGFM",
          "adCount": 0
        },
        {
          "station": "DHAMAAL FM",
          "adCount": 0
        },
        {
          "station": "MYFM",
          "adCount": 0
        },
        {
          "station": "RADIO CITY",
          "adCount": 91
        }
      ]
    },
    {
      "adName": "ADESHWAR MEN'S WEAR",
      "percentage": 0.61,
      "stations": [
        {
          "station": "BIGFM",
          "adCount": 0
        },
        {
          "station": "DHAMAAL FM",
          "adCount": 0
        },
        {
          "station": "MYFM",
          "adCount": 0
        },
        {
          "station": "RADIO CITY",
          "adCount": 91
        }
      ]
    },
    {
      "adName": "NAMCO HOSPITAL",
      "percentage": 0.61,
      "stations": [
        {
          "station": "BIGFM",
          "adCount": 0
        },
        {
          "station": "DHAMAAL FM",
          "adCount": 0
        },
        {
          "station": "MYFM",
          "adCount": 5
        },
        {
          "station": "RADIO CITY",
          "adCount": 86
        }
      ]
    },
    {
      "adName": "TVS",
      "percentage": 0.59,
      "stations": [
        {
          "station": "BIGFM",
          "adCount": 0
        },
        {
          "station": "DHAMAAL FM",
          "adCount": 0
        },
        {
          "station": "MYFM",
          "adCount": 0
        },
        {
          "station": "RADIO CITY",
          "adCount": 88
        }
      ]
    },
    {
      "adName": "NEW ARTS COMMERCE&SCIENCE COLLEGE",
      "percentage": 0.57,
      "stations": [
        {
          "station": "BIGFM",
          "adCount": 0
        },
        {
          "station": "DHAMAAL FM",
          "adCount": 54
        },
        {
          "station": "MYFM",
          "adCount": 31
        },
        {
          "station": "RADIO CITY",
          "adCount": 0
        }
      ]
    },
    {
      "adName": "SACHI SAHELI",
      "percentage": 0.55,
      "stations": [
        {
          "station": "BIGFM",
          "adCount": 18
        },
        {
          "station": "DHAMAAL FM",
          "adCount": 32
        },
        {
          "station": "MYFM",
          "adCount": 32
        },
        {
          "station": "RADIO CITY",
          "adCount": 0
        }
      ]
    },
    {
      "adName": "PATIL HOSPITAL",
      "percentage": 0.53,
      "stations": [
        {
          "station": "BIGFM",
          "adCount": 79
        },
        {
          "station": "DHAMAAL FM",
          "adCount": 0
        },
        {
          "station": "MYFM",
          "adCount": 0
        },
        {
          "station": "RADIO CITY",
          "adCount": 0
        }
      ]
    },
    {
      "adName": "APPASAHEB ALIAS SA. RE. PATIL INSTITUTE OF TECHNOLOGY",
      "percentage": 0.53,
      "stations": [
        {
          "station": "BIGFM",
          "adCount": 0
        },
        {
          "station": "DHAMAAL FM",
          "adCount": 0
        },
        {
          "station": "MYFM",
          "adCount": 0
        },
        {
          "station": "RADIO CITY",
          "adCount": 79
        }
      ]
    },
    {
      "adName": "BADE HOSPITAL AND MATERNITY HOME",
      "percentage": 0.53,
      "stations": [
        {
          "station": "BIGFM",
          "adCount": 79
        },
        {
          "station": "DHAMAAL FM",
          "adCount": 0
        },
        {
          "station": "MYFM",
          "adCount": 0
        },
        {
          "station": "RADIO CITY",
          "adCount": 0
        }
      ]
    },
    {
      "adName": "DR. VITHALRAO VIKHE PATIL COLLEGE",
      "percentage": 0.53,
      "stations": [
        {
          "station": "BIGFM",
          "adCount": 0
        },
        {
          "station": "DHAMAAL FM",
          "adCount": 0
        },
        {
          "station": "MYFM",
          "adCount": 0
        },
        {
          "station": "RADIO CITY",
          "adCount": 79
        }
      ]
    },
    {
      "adName": "LAXMI CHEMICAL PVT LTD",
      "percentage": 0.52,
      "stations": [
        {
          "station": "BIGFM",
          "adCount": 0
        },
        {
          "station": "DHAMAAL FM",
          "adCount": 0
        },
        {
          "station": "MYFM",
          "adCount": 0
        },
        {
          "station": "RADIO CITY",
          "adCount": 78
        }
      ]
    },
    {
      "adName": "NEURON PLUS HOSPITAL",
      "percentage": 0.52,
      "stations": [
        {
          "station": "BIGFM",
          "adCount": 0
        },
        {
          "station": "DHAMAAL FM",
          "adCount": 0
        },
        {
          "station": "MYFM",
          "adCount": 0
        },
        {
          "station": "RADIO CITY",
          "adCount": 78
        }
      ]
    },
    {
      "adName": "ROOP MANTRA",
      "percentage": 0.51,
      "stations": [
        {
          "station": "BIGFM",
          "adCount": 21
        },
        {
          "station": "DHAMAAL FM",
          "adCount": 28
        },
        {
          "station": "MYFM",
          "adCount": 28
        },
        {
          "station": "RADIO CITY",
          "adCount": 0
        }
      ]
    },
    {
      "adName": "VISHVESHWARYA TECHNICAL",
      "percentage": 0.49,
      "stations": [
        {
          "station": "BIGFM",
          "adCount": 0
        },
        {
          "station": "DHAMAAL FM",
          "adCount": 0
        },
        {
          "station": "MYFM",
          "adCount": 0
        },
        {
          "station": "RADIO CITY",
          "adCount": 73
        }
      ]
    },
    {
      "adName": "BENDRE HOSPITAL",
      "percentage": 0.47,
      "stations": [
        {
          "station": "BIGFM",
          "adCount": 0
        },
        {
          "station": "DHAMAAL FM",
          "adCount": 0
        },
        {
          "station": "MYFM",
          "adCount": 0
        },
        {
          "station": "RADIO CITY",
          "adCount": 71
        }
      ]
    },
    {
      "adName": "SNEH RESORT",
      "percentage": 0.47,
      "stations": [
        {
          "station": "BIGFM",
          "adCount": 71
        },
        {
          "station": "DHAMAAL FM",
          "adCount": 0
        },
        {
          "station": "MYFM",
          "adCount": 0
        },
        {
          "station": "RADIO CITY",
          "adCount": 0
        }
      ]
    },
    {
      "adName": "KAKASAHEB MHASKE HOMEOPATHIC MEDICAL COLLEGE",
      "percentage": 0.47,
      "stations": [
        {
          "station": "BIGFM",
          "adCount": 70
        },
        {
          "station": "DHAMAAL FM",
          "adCount": 0
        },
        {
          "station": "MYFM",
          "adCount": 0
        },
        {
          "station": "RADIO CITY",
          "adCount": 0
        }
      ]
    },
    {
      "adName": "NARAYANI",
      "percentage": 0.46,
      "stations": [
        {
          "station": "BIGFM",
          "adCount": 0
        },
        {
          "station": "DHAMAAL FM",
          "adCount": 0
        },
        {
          "station": "MYFM",
          "adCount": 0
        },
        {
          "station": "RADIO CITY",
          "adCount": 69
        }
      ]
    },
    {
      "adName": "SHARAD BANK",
      "percentage": 0.46,
      "stations": [
        {
          "station": "BIGFM",
          "adCount": 0
        },
        {
          "station": "DHAMAAL FM",
          "adCount": 0
        },
        {
          "station": "MYFM",
          "adCount": 69
        },
        {
          "station": "RADIO CITY",
          "adCount": 0
        }
      ]
    },
    {
      "adName": "NUCLEUS HOSPITAL AND RESEARCH CENTER",
      "percentage": 0.45,
      "stations": [
        {
          "station": "BIGFM",
          "adCount": 68
        },
        {
          "station": "DHAMAAL FM",
          "adCount": 0
        },
        {
          "station": "MYFM",
          "adCount": 0
        },
        {
          "station": "RADIO CITY",
          "adCount": 0
        }
      ]
    },
    {
      "adName": "DATTA MARBLE",
      "percentage": 0.45,
      "stations": [
        {
          "station": "BIGFM",
          "adCount": 0
        },
        {
          "station": "DHAMAAL FM",
          "adCount": 68
        },
        {
          "station": "MYFM",
          "adCount": 0
        },
        {
          "station": "RADIO CITY",
          "adCount": 0
        }
      ]
    },
    {
      "adName": "MYFM",
      "percentage": 0.45,
      "stations": [
        {
          "station": "BIGFM",
          "adCount": 0
        },
        {
          "station": "DHAMAAL FM",
          "adCount": 0
        },
        {
          "station": "MYFM",
          "adCount": 68
        },
        {
          "station": "RADIO CITY",
          "adCount": 0
        }
      ]
    },
    {
      "adName": "MVPS\u2019S KBT COE",
      "percentage": 0.45,
      "stations": [
        {
          "station": "BIGFM",
          "adCount": 0
        },
        {
          "station": "DHAMAAL FM",
          "adCount": 0
        },
        {
          "station": "MYFM",
          "adCount": 0
        },
        {
          "station": "RADIO CITY",
          "adCount": 67
        }
      ]
    },
    {
      "adName": "RBI",
      "percentage": 0.44,
      "stations": [
        {
          "station": "BIGFM",
          "adCount": 12
        },
        {
          "station": "DHAMAAL FM",
          "adCount": 9
        },
        {
          "station": "MYFM",
          "adCount": 9
        },
        {
          "station": "RADIO CITY",
          "adCount": 36
        }
      ]
    },
    {
      "adName": "SANJIVANI UNIVERSITY",
      "percentage": 0.43,
      "stations": [
        {
          "station": "BIGFM",
          "adCount": 0
        },
        {
          "station": "DHAMAAL FM",
          "adCount": 0
        },
        {
          "station": "MYFM",
          "adCount": 65
        },
        {
          "station": "RADIO CITY",
          "adCount": 0
        }
      ]
    },
    {
      "adName": "VIJAY GANGA RURAL MEDICAL FOUNDATION",
      "percentage": 0.42,
      "stations": [
        {
          "station": "BIGFM",
          "adCount": 0
        },
        {
          "station": "DHAMAAL FM",
          "adCount": 39
        },
        {
          "station": "MYFM",
          "adCount": 24
        },
        {
          "station": "RADIO CITY",
          "adCount": 0
        }
      ]
    },
    {
      "adName": "VOLKSWAGEN",
      "percentage": 0.41,
      "stations": [
        {
          "station": "BIGFM",
          "adCount": 61
        },
        {
          "station": "DHAMAAL FM",
          "adCount": 0
        },
        {
          "station": "MYFM",
          "adCount": 0
        },
        {
          "station": "RADIO CITY",
          "adCount": 0
        }
      ]
    },
    {
      "adName": "VITTHAL OIL",
      "percentage": 0.41,
      "stations": [
        {
          "station": "BIGFM",
          "adCount": 0
        },
        {
          "station": "DHAMAAL FM",
          "adCount": 42
        },
        {
          "station": "MYFM",
          "adCount": 19
        },
        {
          "station": "RADIO CITY",
          "adCount": 0
        }
      ]
    },
    {
      "adName": "CAMEL SUPERFINE",
      "percentage": 0.4,
      "stations": [
        {
          "station": "BIGFM",
          "adCount": 60
        },
        {
          "station": "DHAMAAL FM",
          "adCount": 0
        },
        {
          "station": "MYFM",
          "adCount": 0
        },
        {
          "station": "RADIO CITY",
          "adCount": 0
        }
      ]
    },
    {
      "adName": "SHRI DATTA MARBLE",
      "percentage": 0.4,
      "stations": [
        {
          "station": "BIGFM",
          "adCount": 0
        },
        {
          "station": "DHAMAAL FM",
          "adCount": 0
        },
        {
          "station": "MYFM",
          "adCount": 60
        },
        {
          "station": "RADIO CITY",
          "adCount": 0
        }
      ]
    },
    {
      "adName": "GENERICART",
      "percentage": 0.4,
      "stations": [
        {
          "station": "BIGFM",
          "adCount": 0
        },
        {
          "station": "DHAMAAL FM",
          "adCount": 0
        },
        {
          "station": "MYFM",
          "adCount": 0
        },
        {
          "station": "RADIO CITY",
          "adCount": 60
        }
      ]
    },
    {
      "adName": "MALABAR JEWELLERY",
      "percentage": 0.37,
      "stations": [
        {
          "station": "BIGFM",
          "adCount": 0
        },
        {
          "station": "DHAMAAL FM",
          "adCount": 0
        },
        {
          "station": "MYFM",
          "adCount": 0
        },
        {
          "station": "RADIO CITY",
          "adCount": 56
        }
      ]
    },
    {
      "adName": "FSSAI",
      "percentage": 0.37,
      "stations": [
        {
          "station": "BIGFM",
          "adCount": 0
        },
        {
          "station": "DHAMAAL FM",
          "adCount": 0
        },
        {
          "station": "MYFM",
          "adCount": 0
        },
        {
          "station": "RADIO CITY",
          "adCount": 55
        }
      ]
    },
    {
      "adName": "GOVERNMENT OF INDIA",
      "percentage": 0.36,
      "stations": [
        {
          "station": "BIGFM",
          "adCount": 0
        },
        {
          "station": "DHAMAAL FM",
          "adCount": 20
        },
        {
          "station": "MYFM",
          "adCount": 16
        },
        {
          "station": "RADIO CITY",
          "adCount": 18
        }
      ]
    },
    {
      "adName": "NAGAR IVF FERTILITY CENTER",
      "percentage": 0.29,
      "stations": [
        {
          "station": "BIGFM",
          "adCount": 0
        },
        {
          "station": "DHAMAAL FM",
          "adCount": 0
        },
        {
          "station": "MYFM",
          "adCount": 0
        },
        {
          "station": "RADIO CITY",
          "adCount": 43
        }
      ]
    },
    {
      "adName": "AMITY UNIVERSITY",
      "percentage": 0.27,
      "stations": [
        {
          "station": "BIGFM",
          "adCount": 0
        },
        {
          "station": "DHAMAAL FM",
          "adCount": 0
        },
        {
          "station": "MYFM",
          "adCount": 0
        },
        {
          "station": "RADIO CITY",
          "adCount": 41
        }
      ]
    },
    {
      "adName": "DHAMAAL",
      "percentage": 0.27,
      "stations": [
        {
          "station": "BIGFM",
          "adCount": 0
        },
        {
          "station": "DHAMAAL FM",
          "adCount": 15
        },
        {
          "station": "MYFM",
          "adCount": 26
        },
        {
          "station": "RADIO CITY",
          "adCount": 0
        }
      ]
    },
    {
      "adName": "SDM COLLEGE",
      "percentage": 0.25,
      "stations": [
        {
          "station": "BIGFM",
          "adCount": 0
        },
        {
          "station": "DHAMAAL FM",
          "adCount": 38
        },
        {
          "station": "MYFM",
          "adCount": 0
        },
        {
          "station": "RADIO CITY",
          "adCount": 0
        }
      ]
    },
    {
      "adName": "PAUL MERCHANTS",
      "percentage": 0.25,
      "stations": [
        {
          "station": "BIGFM",
          "adCount": 0
        },
        {
          "station": "DHAMAAL FM",
          "adCount": 19
        },
        {
          "station": "MYFM",
          "adCount": 18
        },
        {
          "station": "RADIO CITY",
          "adCount": 0
        }
      ]
    },
    {
      "adName": "KAPILA PASHU AAHAR",
      "percentage": 0.23,
      "stations": [
        {
          "station": "BIGFM",
          "adCount": 35
        },
        {
          "station": "DHAMAAL FM",
          "adCount": 0
        },
        {
          "station": "MYFM",
          "adCount": 0
        },
        {
          "station": "RADIO CITY",
          "adCount": 0
        }
      ]
    },
    {
      "adName": "DKTE SOCIETY",
      "percentage": 0.23,
      "stations": [
        {
          "station": "BIGFM",
          "adCount": 0
        },
        {
          "station": "DHAMAAL FM",
          "adCount": 0
        },
        {
          "station": "MYFM",
          "adCount": 0
        },
        {
          "station": "RADIO CITY",
          "adCount": 35
        }
      ]
    },
    {
      "adName": "SANDIP UNIVERSITY",
      "percentage": 0.23,
      "stations": [
        {
          "station": "BIGFM",
          "adCount": 0
        },
        {
          "station": "DHAMAAL FM",
          "adCount": 0
        },
        {
          "station": "MYFM",
          "adCount": 34
        },
        {
          "station": "RADIO CITY",
          "adCount": 0
        }
      ]
    },
    {
      "adName": "SEAL&SALT HOTEL",
      "percentage": 0.23,
      "stations": [
        {
          "station": "BIGFM",
          "adCount": 0
        },
        {
          "station": "DHAMAAL FM",
          "adCount": 0
        },
        {
          "station": "MYFM",
          "adCount": 34
        },
        {
          "station": "RADIO CITY",
          "adCount": 0
        }
      ]
    },
    {
      "adName": "RELIANCE DIGITAL",
      "percentage": 0.21,
      "stations": [
        {
          "station": "BIGFM",
          "adCount": 0
        },
        {
          "station": "DHAMAAL FM",
          "adCount": 0
        },
        {
          "station": "MYFM",
          "adCount": 32
        },
        {
          "station": "RADIO CITY",
          "adCount": 0
        }
      ]
    },
    {
      "adName": "VARMORA GRANITO PVT. LTD.",
      "percentage": 0.21,
      "stations": [
        {
          "station": "BIGFM",
          "adCount": 0
        },
        {
          "station": "DHAMAAL FM",
          "adCount": 0
        },
        {
          "station": "MYFM",
          "adCount": 31
        },
        {
          "station": "RADIO CITY",
          "adCount": 0
        }
      ]
    },
    {
      "adName": "SHETI SUDHAR SAHITYA KENDRA",
      "percentage": 0.21,
      "stations": [
        {
          "station": "BIGFM",
          "adCount": 0
        },
        {
          "station": "DHAMAAL FM",
          "adCount": 0
        },
        {
          "station": "MYFM",
          "adCount": 0
        },
        {
          "station": "RADIO CITY",
          "adCount": 31
        }
      ]
    },
    {
      "adName": "SIGNBOAT AGRO PVT. LTD",
      "percentage": 0.21,
      "stations": [
        {
          "station": "BIGFM",
          "adCount": 0
        },
        {
          "station": "DHAMAAL FM",
          "adCount": 0
        },
        {
          "station": "MYFM",
          "adCount": 0
        },
        {
          "station": "RADIO CITY",
          "adCount": 31
        }
      ]
    },
    {
      "adName": "AJIO",
      "percentage": 0.2,
      "stations": [
        {
          "station": "BIGFM",
          "adCount": 0
        },
        {
          "station": "DHAMAAL FM",
          "adCount": 0
        },
        {
          "station": "MYFM",
          "adCount": 30
        },
        {
          "station": "RADIO CITY",
          "adCount": 0
        }
      ]
    },
    {
      "adName": "VIJAY GANGA RURAL MMEDICAL FOUNDATION",
      "percentage": 0.2,
      "stations": [
        {
          "station": "BIGFM",
          "adCount": 30
        },
        {
          "station": "DHAMAAL FM",
          "adCount": 0
        },
        {
          "station": "MYFM",
          "adCount": 0
        },
        {
          "station": "RADIO CITY",
          "adCount": 0
        }
      ]
    },
    {
      "adName": "SHRI SANT NAGEBABA MULTISTATE CO-OP URBAN CREDIT SOCIETY",
      "percentage": 0.2,
      "stations": [
        {
          "station": "BIGFM",
          "adCount": 0
        },
        {
          "station": "DHAMAAL FM",
          "adCount": 0
        },
        {
          "station": "MYFM",
          "adCount": 30
        },
        {
          "station": "RADIO CITY",
          "adCount": 0
        }
      ]
    },
    {
      "adName": "GARNIER",
      "percentage": 0.2,
      "stations": [
        {
          "station": "BIGFM",
          "adCount": 0
        },
        {
          "station": "DHAMAAL FM",
          "adCount": 0
        },
        {
          "station": "MYFM",
          "adCount": 0
        },
        {
          "station": "RADIO CITY",
          "adCount": 30
        }
      ]
    },
    {
      "adName": "MAS FINANCIAL SERVICES LTD",
      "percentage": 0.19,
      "stations": [
        {
          "station": "BIGFM",
          "adCount": 0
        },
        {
          "station": "DHAMAAL FM",
          "adCount": 0
        },
        {
          "station": "MYFM",
          "adCount": 29
        },
        {
          "station": "RADIO CITY",
          "adCount": 0
        }
      ]
    },
    {
      "adName": "MATRUSEVA WOMEN'S HOSPITAL",
      "percentage": 0.19,
      "stations": [
        {
          "station": "BIGFM",
          "adCount": 0
        },
        {
          "station": "DHAMAAL FM",
          "adCount": 0
        },
        {
          "station": "MYFM",
          "adCount": 29
        },
        {
          "station": "RADIO CITY",
          "adCount": 0
        }
      ]
    },
    {
      "adName": "JIO TV APP",
      "percentage": 0.19,
      "stations": [
        {
          "station": "BIGFM",
          "adCount": 0
        },
        {
          "station": "DHAMAAL FM",
          "adCount": 0
        },
        {
          "station": "MYFM",
          "adCount": 0
        },
        {
          "station": "RADIO CITY",
          "adCount": 29
        }
      ]
    },
    {
      "adName": "TVS SHOWROOM",
      "percentage": 0.19,
      "stations": [
        {
          "station": "BIGFM",
          "adCount": 0
        },
        {
          "station": "DHAMAAL FM",
          "adCount": 0
        },
        {
          "station": "MYFM",
          "adCount": 28
        },
        {
          "station": "RADIO CITY",
          "adCount": 0
        }
      ]
    },
    {
      "adName": "ADSUL EDUCATIONAL CAMPUS",
      "percentage": 0.19,
      "stations": [
        {
          "station": "BIGFM",
          "adCount": 0
        },
        {
          "station": "DHAMAAL FM",
          "adCount": 0
        },
        {
          "station": "MYFM",
          "adCount": 28
        },
        {
          "station": "RADIO CITY",
          "adCount": 0
        }
      ]
    },
    {
      "adName": "PUNJAB NATIONAL BANK",
      "percentage": 0.18,
      "stations": [
        {
          "station": "BIGFM",
          "adCount": 27
        },
        {
          "station": "DHAMAAL FM",
          "adCount": 0
        },
        {
          "station": "MYFM",
          "adCount": 0
        },
        {
          "station": "RADIO CITY",
          "adCount": 0
        }
      ]
    },
    {
      "adName": "AHILYNAGAR MUNICIPAL CORPORATION",
      "percentage": 0.17,
      "stations": [
        {
          "station": "BIGFM",
          "adCount": 0
        },
        {
          "station": "DHAMAAL FM",
          "adCount": 10
        },
        {
          "station": "MYFM",
          "adCount": 16
        },
        {
          "station": "RADIO CITY",
          "adCount": 0
        }
      ]
    },
    {
      "adName": "ALORA",
      "percentage": 0.17,
      "stations": [
        {
          "station": "BIGFM",
          "adCount": 0
        },
        {
          "station": "DHAMAAL FM",
          "adCount": 0
        },
        {
          "station": "MYFM",
          "adCount": 25
        },
        {
          "station": "RADIO CITY",
          "adCount": 0
        }
      ]
    },
    {
      "adName": "AD : MY FM",
      "percentage": 0.15,
      "stations": [
        {
          "station": "BIGFM",
          "adCount": 0
        },
        {
          "station": "DHAMAAL FM",
          "adCount": 0
        },
        {
          "station": "MYFM",
          "adCount": 23
        },
        {
          "station": "RADIO CITY",
          "adCount": 0
        }
      ]
    },
    {
      "adName": "PRAVARA RURAL ENGINEERING COLLEGE",
      "percentage": 0.15,
      "stations": [
        {
          "station": "BIGFM",
          "adCount": 0
        },
        {
          "station": "DHAMAAL FM",
          "adCount": 0
        },
        {
          "station": "MYFM",
          "adCount": 22
        },
        {
          "station": "RADIO CITY",
          "adCount": 0
        }
      ]
    },
    {
      "adName": "R S BAFNA JWELLERS",
      "percentage": 0.14,
      "stations": [
        {
          "station": "BIGFM",
          "adCount": 0
        },
        {
          "station": "DHAMAAL FM",
          "adCount": 0
        },
        {
          "station": "MYFM",
          "adCount": 21
        },
        {
          "station": "RADIO CITY",
          "adCount": 0
        }
      ]
    },
    {
      "adName": "HORIZON HOSPITAL",
      "percentage": 0.14,
      "stations": [
        {
          "station": "BIGFM",
          "adCount": 0
        },
        {
          "station": "DHAMAAL FM",
          "adCount": 0
        },
        {
          "station": "MYFM",
          "adCount": 0
        },
        {
          "station": "RADIO CITY",
          "adCount": 21
        }
      ]
    },
    {
      "adName": "HYUNDAI",
      "percentage": 0.14,
      "stations": [
        {
          "station": "BIGFM",
          "adCount": 0
        },
        {
          "station": "DHAMAAL FM",
          "adCount": 0
        },
        {
          "station": "MYFM",
          "adCount": 21
        },
        {
          "station": "RADIO CITY",
          "adCount": 0
        }
      ]
    },
    {
      "adName": "N. D. KASAR INSTITUTE OF ENGINEERING AND TECHNOLOGY",
      "percentage": 0.14,
      "stations": [
        {
          "station": "BIGFM",
          "adCount": 0
        },
        {
          "station": "DHAMAAL FM",
          "adCount": 0
        },
        {
          "station": "MYFM",
          "adCount": 21
        },
        {
          "station": "RADIO CITY",
          "adCount": 0
        }
      ]
    },
    {
      "adName": "M.R. JAMGAONKAR",
      "percentage": 0.14,
      "stations": [
        {
          "station": "BIGFM",
          "adCount": 0
        },
        {
          "station": "DHAMAAL FM",
          "adCount": 0
        },
        {
          "station": "MYFM",
          "adCount": 0
        },
        {
          "station": "RADIO CITY",
          "adCount": 21
        }
      ]
    },
    {
      "adName": "DR. MAGAR DENTAL&IMPLANT CENTER",
      "percentage": 0.13,
      "stations": [
        {
          "station": "BIGFM",
          "adCount": 0
        },
        {
          "station": "DHAMAAL FM",
          "adCount": 0
        },
        {
          "station": "MYFM",
          "adCount": 19
        },
        {
          "station": "RADIO CITY",
          "adCount": 0
        }
      ]
    },
    {
      "adName": "SBI KISAN CREDIT CARD (KCC)",
      "percentage": 0.12,
      "stations": [
        {
          "station": "BIGFM",
          "adCount": 0
        },
        {
          "station": "DHAMAAL FM",
          "adCount": 0
        },
        {
          "station": "MYFM",
          "adCount": 18
        },
        {
          "station": "RADIO CITY",
          "adCount": 0
        }
      ]
    },
    {
      "adName": "IMS ENGINEERING COLLEGE",
      "percentage": 0.12,
      "stations": [
        {
          "station": "BIGFM",
          "adCount": 0
        },
        {
          "station": "DHAMAAL FM",
          "adCount": 0
        },
        {
          "station": "MYFM",
          "adCount": 18
        },
        {
          "station": "RADIO CITY",
          "adCount": 0
        }
      ]
    },
    {
      "adName": "G H RAISONI COLLEGE OF ENGINEERING AND MANAGEMENT",
      "percentage": 0.11,
      "stations": [
        {
          "station": "BIGFM",
          "adCount": 0
        },
        {
          "station": "DHAMAAL FM",
          "adCount": 0
        },
        {
          "station": "MYFM",
          "adCount": 17
        },
        {
          "station": "RADIO CITY",
          "adCount": 0
        }
      ]
    },
    {
      "adName": "SNEHDEEP SUPER SPECIALITY HOSPITAL",
      "percentage": 0.11,
      "stations": [
        {
          "station": "BIGFM",
          "adCount": 0
        },
        {
          "station": "DHAMAAL FM",
          "adCount": 0
        },
        {
          "station": "MYFM",
          "adCount": 16
        },
        {
          "station": "RADIO CITY",
          "adCount": 0
        }
      ]
    },
    {
      "adName": "RC PATEL PHARMACY COLLEGE",
      "percentage": 0.11,
      "stations": [
        {
          "station": "BIGFM",
          "adCount": 0
        },
        {
          "station": "DHAMAAL FM",
          "adCount": 0
        },
        {
          "station": "MYFM",
          "adCount": 16
        },
        {
          "station": "RADIO CITY",
          "adCount": 0
        }
      ]
    },
    {
      "adName": "S N HORANE INTERIORS AND CUBIC DESIGN STUDIO",
      "percentage": 0.11,
      "stations": [
        {
          "station": "BIGFM",
          "adCount": 0
        },
        {
          "station": "DHAMAAL FM",
          "adCount": 0
        },
        {
          "station": "MYFM",
          "adCount": 16
        },
        {
          "station": "RADIO CITY",
          "adCount": 0
        }
      ]
    },
    {
      "adName": "PADMASHREE DR.VITHALRAO VIKHE PATIL FOUNDATION\u2019S COLLEGE OF PHARMACY",
      "percentage": 0.11,
      "stations": [
        {
          "station": "BIGFM",
          "adCount": 16
        },
        {
          "station": "DHAMAAL FM",
          "adCount": 0
        },
        {
          "station": "MYFM",
          "adCount": 0
        },
        {
          "station": "RADIO CITY",
          "adCount": 0
        }
      ]
    },
    {
      "adName": "DWARKADAS SHAMKUMAR",
      "percentage": 0.09,
      "stations": [
        {
          "station": "BIGFM",
          "adCount": 0
        },
        {
          "station": "DHAMAAL FM",
          "adCount": 0
        },
        {
          "station": "MYFM",
          "adCount": 14
        },
        {
          "station": "RADIO CITY",
          "adCount": 0
        }
      ]
    },
    {
      "adName": "SHUBHKIRTI LAWNS&RESORT",
      "percentage": 0.07,
      "stations": [
        {
          "station": "BIGFM",
          "adCount": 0
        },
        {
          "station": "DHAMAAL FM",
          "adCount": 0
        },
        {
          "station": "MYFM",
          "adCount": 11
        },
        {
          "station": "RADIO CITY",
          "adCount": 0
        }
      ]
    },
    {
      "adName": "SAPKAL KNOWLEDGE HUB",
      "percentage": 0.07,
      "stations": [
        {
          "station": "BIGFM",
          "adCount": 0
        },
        {
          "station": "DHAMAAL FM",
          "adCount": 0
        },
        {
          "station": "MYFM",
          "adCount": 10
        },
        {
          "station": "RADIO CITY",
          "adCount": 0
        }
      ]
    },
    {
      "adName": "WARANA",
      "percentage": 0.07,
      "stations": [
        {
          "station": "BIGFM",
          "adCount": 0
        },
        {
          "station": "DHAMAAL FM",
          "adCount": 0
        },
        {
          "station": "MYFM",
          "adCount": 10
        },
        {
          "station": "RADIO CITY",
          "adCount": 0
        }
      ]
    },
    {
      "adName": "RAM AGENCY",
      "percentage": 0.07,
      "stations": [
        {
          "station": "BIGFM",
          "adCount": 0
        },
        {
          "station": "DHAMAAL FM",
          "adCount": 0
        },
        {
          "station": "MYFM",
          "adCount": 10
        },
        {
          "station": "RADIO CITY",
          "adCount": 0
        }
      ]
    },
    {
      "adName": "GEETANJALI BOOTH HOSPITAL",
      "percentage": 0.07,
      "stations": [
        {
          "station": "BIGFM",
          "adCount": 0
        },
        {
          "station": "DHAMAAL FM",
          "adCount": 0
        },
        {
          "station": "MYFM",
          "adCount": 10
        },
        {
          "station": "RADIO CITY",
          "adCount": 0
        }
      ]
    },
    {
      "adName": "N N SATTHA",
      "percentage": 0.06,
      "stations": [
        {
          "station": "BIGFM",
          "adCount": 0
        },
        {
          "station": "DHAMAAL FM",
          "adCount": 0
        },
        {
          "station": "MYFM",
          "adCount": 9
        },
        {
          "station": "RADIO CITY",
          "adCount": 0
        }
      ]
    },
    {
      "adName": "AMRIT VAHINI",
      "percentage": 0.06,
      "stations": [
        {
          "station": "BIGFM",
          "adCount": 0
        },
        {
          "station": "DHAMAAL FM",
          "adCount": 0
        },
        {
          "station": "MYFM",
          "adCount": 9
        },
        {
          "station": "RADIO CITY",
          "adCount": 0
        }
      ]
    },
    {
      "adName": "G.A. GAIKWAD HOSPITAL",
      "percentage": 0.06,
      "stations": [
        {
          "station": "BIGFM",
          "adCount": 0
        },
        {
          "station": "DHAMAAL FM",
          "adCount": 0
        },
        {
          "station": "MYFM",
          "adCount": 9
        },
        {
          "station": "RADIO CITY",
          "adCount": 0
        }
      ]
    },
    {
      "adName": "INDIAN AIR FORCE",
      "percentage": 0.05,
      "stations": [
        {
          "station": "BIGFM",
          "adCount": 0
        },
        {
          "station": "DHAMAAL FM",
          "adCount": 4
        },
        {
          "station": "MYFM",
          "adCount": 4
        },
        {
          "station": "RADIO CITY",
          "adCount": 0
        }
      ]
    },
    {
      "adName": "CANARA",
      "percentage": 0.05,
      "stations": [
        {
          "station": "BIGFM",
          "adCount": 0
        },
        {
          "station": "DHAMAAL FM",
          "adCount": 0
        },
        {
          "station": "MYFM",
          "adCount": 0
        },
        {
          "station": "RADIO CITY",
          "adCount": 8
        }
      ]
    },
    {
      "adName": "VARAD NETRALAY EYE HOSPITAL",
      "percentage": 0.05,
      "stations": [
        {
          "station": "BIGFM",
          "adCount": 0
        },
        {
          "station": "DHAMAAL FM",
          "adCount": 0
        },
        {
          "station": "MYFM",
          "adCount": 0
        },
        {
          "station": "RADIO CITY",
          "adCount": 8
        }
      ]
    },
    {
      "adName": "MAULI SANDHIVAT CLINIC",
      "percentage": 0.05,
      "stations": [
        {
          "station": "BIGFM",
          "adCount": 0
        },
        {
          "station": "DHAMAAL FM",
          "adCount": 0
        },
        {
          "station": "MYFM",
          "adCount": 7
        },
        {
          "station": "RADIO CITY",
          "adCount": 0
        }
      ]
    },
    {
      "adName": "LA PINOZ'S PIZZA",
      "percentage": 0.05,
      "stations": [
        {
          "station": "BIGFM",
          "adCount": 0
        },
        {
          "station": "DHAMAAL FM",
          "adCount": 0
        },
        {
          "station": "MYFM",
          "adCount": 7
        },
        {
          "station": "RADIO CITY",
          "adCount": 0
        }
      ]
    },
    {
      "adName": "M.R.JAMGAONKAR",
      "percentage": 0.05,
      "stations": [
        {
          "station": "BIGFM",
          "adCount": 7
        },
        {
          "station": "DHAMAAL FM",
          "adCount": 0
        },
        {
          "station": "MYFM",
          "adCount": 0
        },
        {
          "station": "RADIO CITY",
          "adCount": 0
        }
      ]
    },
    {
      "adName": "N N SATHA COLLEGE OF PHARMACY",
      "percentage": 0.05,
      "stations": [
        {
          "station": "BIGFM",
          "adCount": 0
        },
        {
          "station": "DHAMAAL FM",
          "adCount": 0
        },
        {
          "station": "MYFM",
          "adCount": 7
        },
        {
          "station": "RADIO CITY",
          "adCount": 0
        }
      ]
    },
    {
      "adName": "DR. AMIT PALWADE",
      "percentage": 0.04,
      "stations": [
        {
          "station": "BIGFM",
          "adCount": 0
        },
        {
          "station": "DHAMAAL FM",
          "adCount": 0
        },
        {
          "station": "MYFM",
          "adCount": 0
        },
        {
          "station": "RADIO CITY",
          "adCount": 6
        }
      ]
    },
    {
      "adName": "PALVE GASTRO CLINIC",
      "percentage": 0.04,
      "stations": [
        {
          "station": "BIGFM",
          "adCount": 0
        },
        {
          "station": "DHAMAAL FM",
          "adCount": 0
        },
        {
          "station": "MYFM",
          "adCount": 6
        },
        {
          "station": "RADIO CITY",
          "adCount": 0
        }
      ]
    },
    {
      "adName": "GK TMT",
      "percentage": 0.04,
      "stations": [
        {
          "station": "BIGFM",
          "adCount": 0
        },
        {
          "station": "DHAMAAL FM",
          "adCount": 0
        },
        {
          "station": "MYFM",
          "adCount": 6
        },
        {
          "station": "RADIO CITY",
          "adCount": 0
        }
      ]
    },
    {
      "adName": "BOMBAY ACADEMY OF FINE ARTS",
      "percentage": 0.04,
      "stations": [
        {
          "station": "BIGFM",
          "adCount": 0
        },
        {
          "station": "DHAMAAL FM",
          "adCount": 0
        },
        {
          "station": "MYFM",
          "adCount": 6
        },
        {
          "station": "RADIO CITY",
          "adCount": 0
        }
      ]
    },
    {
      "adName": "AMBUJA CEMENT",
      "percentage": 0.03,
      "stations": [
        {
          "station": "BIGFM",
          "adCount": 0
        },
        {
          "station": "DHAMAAL FM",
          "adCount": 0
        },
        {
          "station": "MYFM",
          "adCount": 5
        },
        {
          "station": "RADIO CITY",
          "adCount": 0
        }
      ]
    },
    {
      "adName": "GOVT OF MAHARASHTRA",
      "percentage": 0.03,
      "stations": [
        {
          "station": "BIGFM",
          "adCount": 0
        },
        {
          "station": "DHAMAAL FM",
          "adCount": 5
        },
        {
          "station": "MYFM",
          "adCount": 0
        },
        {
          "station": "RADIO CITY",
          "adCount": 0
        }
      ]
    },
    {
      "adName": "BANSON YAMAHA SHOWROOM",
      "percentage": 0.03,
      "stations": [
        {
          "station": "BIGFM",
          "adCount": 0
        },
        {
          "station": "DHAMAAL FM",
          "adCount": 0
        },
        {
          "station": "MYFM",
          "adCount": 5
        },
        {
          "station": "RADIO CITY",
          "adCount": 0
        }
      ]
    },
    {
      "adName": "KBT COLLEGE OF ENGINEERING",
      "percentage": 0.03,
      "stations": [
        {
          "station": "BIGFM",
          "adCount": 0
        },
        {
          "station": "DHAMAAL FM",
          "adCount": 0
        },
        {
          "station": "MYFM",
          "adCount": 0
        },
        {
          "station": "RADIO CITY",
          "adCount": 5
        }
      ]
    },
    {
      "adName": "MICROFINE",
      "percentage": 0.03,
      "stations": [
        {
          "station": "BIGFM",
          "adCount": 0
        },
        {
          "station": "DHAMAAL FM",
          "adCount": 0
        },
        {
          "station": "MYFM",
          "adCount": 5
        },
        {
          "station": "RADIO CITY",
          "adCount": 0
        }
      ]
    },
    {
      "adName": "ACC CEMENT",
      "percentage": 0.03,
      "stations": [
        {
          "station": "BIGFM",
          "adCount": 0
        },
        {
          "station": "DHAMAAL FM",
          "adCount": 0
        },
        {
          "station": "MYFM",
          "adCount": 4
        },
        {
          "station": "RADIO CITY",
          "adCount": 0
        }
      ]
    },
    {
      "adName": "THYME&WHISK",
      "percentage": 0.03,
      "stations": [
        {
          "station": "BIGFM",
          "adCount": 0
        },
        {
          "station": "DHAMAAL FM",
          "adCount": 0
        },
        {
          "station": "MYFM",
          "adCount": 0
        },
        {
          "station": "RADIO CITY",
          "adCount": 4
        }
      ]
    },
    {
      "adName": "NDTV",
      "percentage": 0.03,
      "stations": [
        {
          "station": "BIGFM",
          "adCount": 0
        },
        {
          "station": "DHAMAAL FM",
          "adCount": 0
        },
        {
          "station": "MYFM",
          "adCount": 4
        },
        {
          "station": "RADIO CITY",
          "adCount": 0
        }
      ]
    },
    {
      "adName": "DR. REKHA ZAWARE PATIL",
      "percentage": 0.03,
      "stations": [
        {
          "station": "BIGFM",
          "adCount": 0
        },
        {
          "station": "DHAMAAL FM",
          "adCount": 0
        },
        {
          "station": "MYFM",
          "adCount": 4
        },
        {
          "station": "RADIO CITY",
          "adCount": 0
        }
      ]
    },
    {
      "adName": "DR CHANDRAKANT KAR",
      "percentage": 0.02,
      "stations": [
        {
          "station": "BIGFM",
          "adCount": 0
        },
        {
          "station": "DHAMAAL FM",
          "adCount": 0
        },
        {
          "station": "MYFM",
          "adCount": 0
        },
        {
          "station": "RADIO CITY",
          "adCount": 3
        }
      ]
    },
    {
      "adName": "DHAMAAL FM",
      "percentage": 0.02,
      "stations": [
        {
          "station": "BIGFM",
          "adCount": 0
        },
        {
          "station": "DHAMAAL FM",
          "adCount": 3
        },
        {
          "station": "MYFM",
          "adCount": 0
        },
        {
          "station": "RADIO CITY",
          "adCount": 0
        }
      ]
    },
    {
      "adName": "BIG LIFE.COM",
      "percentage": 0.02,
      "stations": [
        {
          "station": "BIGFM",
          "adCount": 3
        },
        {
          "station": "DHAMAAL FM",
          "adCount": 0
        },
        {
          "station": "MYFM",
          "adCount": 0
        },
        {
          "station": "RADIO CITY",
          "adCount": 0
        }
      ]
    },
    {
      "adName": "VIJAYSHREE ACADEMY",
      "percentage": 0.02,
      "stations": [
        {
          "station": "BIGFM",
          "adCount": 0
        },
        {
          "station": "DHAMAAL FM",
          "adCount": 0
        },
        {
          "station": "MYFM",
          "adCount": 3
        },
        {
          "station": "RADIO CITY",
          "adCount": 0
        }
      ]
    },
    {
      "adName": "HERITAGE INFRASPACE",
      "percentage": 0.01,
      "stations": [
        {
          "station": "BIGFM",
          "adCount": 1
        },
        {
          "station": "DHAMAAL FM",
          "adCount": 0
        },
        {
          "station": "MYFM",
          "adCount": 0
        },
        {
          "station": "RADIO CITY",
          "adCount": 0
        }
      ]
    },
    {
      "adName": "DR.VITHALRAO VIKHE PATIL FOUNDATION",
      "percentage": 0.01,
      "stations": [
        {
          "station": "BIGFM",
          "adCount": 0
        },
        {
          "station": "DHAMAAL FM",
          "adCount": 0
        },
        {
          "station": "MYFM",
          "adCount": 1
        },
        {
          "station": "RADIO CITY",
          "adCount": 0
        }
      ]
    },
    {
      "adName": "JEEVAN JYOTI ENGLISH MEDIUM SCHOOL AND JR. COLLEGE",
      "percentage": 0.01,
      "stations": [
        {
          "station": "BIGFM",
          "adCount": 0
        },
        {
          "station": "DHAMAAL FM",
          "adCount": 0
        },
        {
          "station": "MYFM",
          "adCount": 1
        },
        {
          "station": "RADIO CITY",
          "adCount": 0
        }
      ]
    },
    {
      "adName": "YAMAHA",
      "percentage": 0.01,
      "stations": [
        {
          "station": "BIGFM",
          "adCount": 0
        },
        {
          "station": "DHAMAAL FM",
          "adCount": 0
        },
        {
          "station": "MYFM",
          "adCount": 1
        },
        {
          "station": "RADIO CITY",
          "adCount": 0
        }
      ]
    }
  ]
}
